metrics/__init__.py
metrics/metrics.py
mllearn/__init__.py
mllearn/alg_adapt/__init__.py
mllearn/alg_adapt/mldt.py
mllearn/alg_adapt/mlknn.py
mllearn/metrics/__init__.py
mllearn/metrics/metrics.py
mllearn/problem_transform/__init__.py
mllearn/problem_transform/br.py
mllearn/problem_transform/cc.py
mllearn/problem_transform/clr.py
mllearn/problem_transform/klabelsets.py
mllearn-1.2.3.dist-info/DESCRIPTION.rst
mllearn-1.2.3.dist-info/LICENSE.txt
mllearn-1.2.3.dist-info/METADATA
mllearn-1.2.3.dist-info/RECORD
mllearn-1.2.3.dist-info/WHEEL
mllearn-1.2.3.dist-info/entry_points.txt
mllearn-1.2.3.dist-info/metadata.json
mllearn-1.2.3.dist-info/top_level.txt
stats/__init__.py
stats/metrics.py
